rust_result/__init__.py
rust_result/result.py
rust_result-0.2.1.dist-info/LICENSE
rust_result-0.2.1.dist-info/METADATA
rust_result-0.2.1.dist-info/WHEEL
rust_result-0.2.1.dist-info/RECORD
