Metadata-Version: 2.1
Name: rust-result
Version: 0.2.1
Summary: 
License: MIT
Author: Ole Kliemann
Author-email: mail@olekliemann.de
Requires-Python: >=3.10
Classifier: License :: OSI Approved :: MIT License
Classifier: Programming Language :: Python :: 3
Classifier: Programming Language :: Python :: 3.10
Classifier: Programming Language :: Python :: 3.11
Classifier: Programming Language :: Python :: 3.12
